{
  "name": "pathed.skill.tiers.diamond.name",
  "description": "pathed.skill.tiers.diamond.desc",
  "category": "pathed:tiers",
  "node_type": "goal",
  "type": "pathed:progression",
  "position": {
    "x": 180,
    "y": 0
  },
  "icon": {
    "type": "item",
    "value": "minecraft:diamond"
  },
  "previous_nodes": [
    "pathed:tiers/iron"
  ],
  "prerequisites": [
    "pathed:tiers/iron",
    "pathed:tiers/gold"
  ],
  "requirements": [
    {
      "type": "pathed:stat_count",
      "stat": "blocks_broken",
      "target": "minecraft:diamond_ore",
      "count": 1,
      "consumed": false
    }
  ],
  "rewards": [
    {
      "type": "pathed:attribute",
      "attribute": "pathed:tier",
      "level": 4
    }
  ]
}